taskforceagents/__init__.py
taskforceagents/__main__.py
taskforceagents/agent.py
taskforceagents/cache.py
taskforceagents/cli.py
taskforceagents/config.py
taskforceagents/models.py
taskforceagents/sse_helpers.py
taskforceagents-0.0.3.dist-info/LICENSE
taskforceagents-0.0.3.dist-info/METADATA
taskforceagents-0.0.3.dist-info/WHEEL
taskforceagents-0.0.3.dist-info/entry_points.txt
taskforceagents-0.0.3.dist-info/RECORD
